MANIFEST.in
README.md
pyproject.toml
requirements.txt
setup.cfg
src/llm/__init__.py
src/llm/prompt_chains/__init__.py
src/llm/prompt_chains/get_table.py
src/llm/prompt_chains/prompt_chains.py
src/llm/prompt_chains/queries/data.sql
src/llm_ds_mkt_lib_prompt_chains.egg-info/PKG-INFO
src/llm_ds_mkt_lib_prompt_chains.egg-info/SOURCES.txt
src/llm_ds_mkt_lib_prompt_chains.egg-info/dependency_links.txt
src/llm_ds_mkt_lib_prompt_chains.egg-info/entry_points.txt
src/llm_ds_mkt_lib_prompt_chains.egg-info/namespace_packages.txt
src/llm_ds_mkt_lib_prompt_chains.egg-info/requires.txt
src/llm_ds_mkt_lib_prompt_chains.egg-info/top_level.txt
src/prompt_chains.egg-info/PKG-INFO
src/prompt_chains.egg-info/SOURCES.txt
src/prompt_chains.egg-info/dependency_links.txt
src/prompt_chains.egg-info/entry_points.txt
src/prompt_chains.egg-info/namespace_packages.txt
src/prompt_chains.egg-info/requires.txt
src/prompt_chains.egg-info/top_level.txt
tests/test_prompt_chains.py