Metadata-Version: 2.1
Name: prompt-chains
Version: 0.0.1
Summary: ds-prompt-chains
Home-page: https://github.com/iuiu34/litchain
Author: llm
Author-email: ds-mkt@llm.com
License: COPYRIGHT
Keywords: ds-prompt-chains
Classifier: Development Status :: 2 - Pre-Alpha
Classifier: Programming Language :: Python :: 3 :: Only
Classifier: Programming Language :: Python :: 3.9
Requires-Dist: fire
Requires-Dist: ds-mkt-utils-bq
